testfn/__init__.py
testfn/analytics.py
testfn/core.py
testfn/reporters.py
testfn/runner.py
testfn/storage.py
testfn/types.py
testfn/visual.py
testfn/adapters/pytest.py
testfn-0.0.1.dist-info/METADATA
testfn-0.0.1.dist-info/WHEEL
testfn-0.0.1.dist-info/RECORD
