Metadata-Version: 2.4
Name: testfn
Version: 0.0.1
Summary: Comprehensive self-hosted testing platform for developers (Python SDK)
Project-URL: Documentation, https://docs.superfunctions.dev/testfn
Project-URL: Repository, https://github.com/21nCo/super-functions
Project-URL: Issues, https://github.com/21nCo/super-functions/issues
Author: 21n
License-Expression: MIT
Keywords: automation,superfunctions,test-runner,testing
Classifier: Development Status :: 3 - Alpha
Classifier: Intended Audience :: Developers
Classifier: License :: OSI Approved :: MIT License
Classifier: Programming Language :: Python :: 3
Classifier: Programming Language :: Python :: 3.10
Classifier: Programming Language :: Python :: 3.11
Classifier: Programming Language :: Python :: 3.12
Classifier: Topic :: Software Development :: Testing
Requires-Python: >=3.10
Requires-Dist: pillow>=10.0.0
Requires-Dist: pydantic>=2.5.0
Requires-Dist: sqlalchemy>=2.0.0
Provides-Extra: dev
Requires-Dist: black>=23.11.0; extra == 'dev'
Requires-Dist: mypy>=1.7.0; extra == 'dev'
Requires-Dist: pytest-asyncio>=0.21.0; extra == 'dev'
Requires-Dist: pytest-cov>=4.1.0; extra == 'dev'
Requires-Dist: pytest>=7.4.0; extra == 'dev'
Requires-Dist: ruff>=0.1.6; extra == 'dev'
